rdeditor/Mendelev_extract.py
rdeditor/__init__.py
rdeditor/_version.py
rdeditor/molEditWidget.py
rdeditor/molViewWidget.py
rdeditor/ptable.py
rdeditor/ptable_widget.py
rdeditor/rdEditor.py
rdeditor/templatehandler.py
rdeditor/utilities.py
rdeditor/icon_themes/dark/index.theme
rdeditor/icon_themes/dark/application/Change_E_Z.png
rdeditor/icon_themes/dark/application/Change_E_Z.svg
rdeditor/icon_themes/dark/application/Change_R_S.png
rdeditor/icon_themes/dark/application/CleanupChem.png
rdeditor/icon_themes/dark/application/RecalcCoord.png
rdeditor/icon_themes/dark/application/about.png
rdeditor/icon_themes/dark/application/appicon.png
rdeditor/icon_themes/dark/application/atommapnumber.png
rdeditor/icon_themes/dark/application/benzene.png
rdeditor/icon_themes/dark/application/calc.png
rdeditor/icon_themes/dark/application/convert.sh
rdeditor/icon_themes/dark/application/cyclohexane.png
rdeditor/icon_themes/dark/application/exit.png
rdeditor/icon_themes/dark/application/grid.png
rdeditor/icon_themes/dark/application/icons8-Broom.png
rdeditor/icon_themes/dark/application/icons8-Bulleted List.png
rdeditor/icon_themes/dark/application/icons8-Cancel.png
rdeditor/icon_themes/dark/application/icons8-Carbon.png
rdeditor/icon_themes/dark/application/icons8-Cursor.png
rdeditor/icon_themes/dark/application/icons8-Decrease Font.png
rdeditor/icon_themes/dark/application/icons8-Delete.png
rdeditor/icon_themes/dark/application/icons8-Double.png
rdeditor/icon_themes/dark/application/icons8-Edit.png
rdeditor/icon_themes/dark/application/icons8-Exit.png
rdeditor/icon_themes/dark/application/icons8-Hydrogen.png
rdeditor/icon_themes/dark/application/icons8-Increase Font.png
rdeditor/icon_themes/dark/application/icons8-Info.png
rdeditor/icon_themes/dark/application/icons8-Left.png
rdeditor/icon_themes/dark/application/icons8-Line.png
rdeditor/icon_themes/dark/application/icons8-Minus.png
rdeditor/icon_themes/dark/application/icons8-Molecule.png
rdeditor-0.5.1.dist-info/LICENSE
rdeditor-0.5.1.dist-info/METADATA
rdeditor-0.5.1.dist-info/WHEEL
rdeditor-0.5.1.dist-info/entry_points.txt
rdeditor-0.5.1.dist-info/top_level.txt
rdeditor-0.5.1.dist-info/RECORD
