Metadata-Version: 2.1
Name: rdeditor
Version: 0.5.1
Summary: An RDKit based molecule editor using PySide
Author-email: Esben Jannik Bjerrum <esbenjannik@rocketmail.com>
License: LGPL
Project-URL: Homepage, http://github.com/ebjerrum/rdeditor
Project-URL: Bug Tracker, https://github.com/ebjerrum/rdeditor/issues
Project-URL: Documentation, https://github.com/ebjerrum/rdeditor/blob/master/README.md
Project-URL: Source Code, https://github.com/ebjerrum/rdeditor
Project-URL: Citation, https://github.com/ebjerrum/rdeditor/blob/master/CITATION.md
Project-URL: ChemRxiv Preprint, https://chemrxiv.org/engage/chemrxiv/article-details/65e6dcfa9138d23161b2979c
Project-URL: Developer Guide, https://github.com/ebjerrum/rdeditor/blob/master/DEVELOPER.md
Keywords: RDKit,molecule,editor,pyside
Requires-Python: >=3.10
License-File: LICENSE
Requires-Dist: PySide6
Requires-Dist: numpy
Requires-Dist: rdkit
Requires-Dist: pyqtdarktheme
Provides-Extra: dev
Requires-Dist: ruff ; extra == 'dev'
Requires-Dist: wheel ; extra == 'dev'
Requires-Dist: twine ; extra == 'dev'
Requires-Dist: setuptools-scm ; extra == 'dev'
